{"device_checker": [], "device_checker.DeviceChecker.__init__": [], "device_checker.DeviceChecker.CheckSimple": ["<builtin>.print", "caffe2.python.workspace.RunOperatorOnce", "caffe2.python.workspace.ResetWorkspace", "<builtin>.len", "<builtin>.range", "numpy.max", "numpy.array", "caffe2.python.core.InferOpBlobDevicesAsDict", "caffe2.python.workspace.CurrentWorkspace", "copy.deepcopy", "caffe2.python.workspace.FetchBlob", "numpy.abs", "numpy.allclose", "caffe2.python.workspace.FeedBlob", "<builtin>.enumerate", "caffe2.python.workspace.SwitchWorkspace"], "copy.deepcopy": [], "caffe2.python.workspace.CurrentWorkspace": [], "caffe2.python.workspace.SwitchWorkspace": [], "<builtin>.enumerate": [], "caffe2.python.core.InferOpBlobDevicesAsDict": [], "<builtin>.print": [], "numpy.array": [], "caffe2.python.workspace.FeedBlob": [], "caffe2.python.workspace.RunOperatorOnce": [], "caffe2.python.workspace.FetchBlob": [], "caffe2.python.workspace.ResetWorkspace": [], "<builtin>.len": [], "<builtin>.range": [], "numpy.allclose": [], "numpy.abs": [], "numpy.max": [], "device_checker.DeviceChecker.CheckNet": ["<builtin>.set", "<builtin>.sum", "<builtin>.len", "<builtin>.range", "<builtin>.print", "numpy.max", "caffe2.python.workspace.RunNetOnce", "caffe2.python.workspace.CurrentWorkspace", "caffe2.python.workspace.FetchBlob", "numpy.abs", "<builtin>.list", "numpy.allclose", "caffe2.python.workspace.FeedBlob", "caffe2.python.workspace.SwitchWorkspace", "future.utils.viewitems"], "<builtin>.set": [], "<builtin>.list": [], "<builtin>.sum": [], "future.utils.viewitems": [], "caffe2.python.workspace.RunNetOnce": []}