{"core": ["dispatch.dispatch"], "dispatch.dispatch": [], "core._reify": ["core.reify", "<builtin>.map", "functools.partial", "<builtin>.dict", "<builtin>.tuple", "<builtin>.iter", "<builtin>.list"], "functools.partial": [], "<builtin>.map": [], "<builtin>.iter": [], "core.reify": ["core.reify", "variable.isvar", "core._reify"], "<builtin>.tuple": [], "<builtin>.list": [], "<builtin>.dict": [], "variable.isvar": [], "core._unify": ["<builtin>.zip", "<builtin>.len", "core.unify"], "<builtin>.len": [], "<builtin>.zip": [], "core.unify": ["variable.isvar", "unification_tools.assoc", "core.unify", "utils.transitive_get", "core._unify"], "utils.transitive_get": [], "unification_tools.assoc": []}