{"graph": [], "graph.saved_tensors_hooks.__init__": [], "graph.saved_tensors_hooks.__enter__": ["torch._C._autograd._register_default_hooks"], "torch._C._autograd._register_default_hooks": [], "graph.saved_tensors_hooks.__exit__": ["torch._C._autograd._reset_default_hooks"], "torch._C._autograd._reset_default_hooks": [], "graph.save_on_cpu.__init__": [], "graph.save_on_cpu.__init__.pack_to_cpu": ["torch.cuda.is_available", "torch.empty"], "torch.cuda.is_available": [], "torch.empty": [], "graph.save_on_cpu.__init__.unpack_from_cpu": [], "graph.save_on_cpu.__enter__": ["torch._C._autograd._register_default_hooks"], "graph.save_on_cpu.__exit__": ["torch._C._autograd._reset_default_hooks"]}