{"framework.load_library": ["util.deprecation.deprecated", "util.tf_export.tf_export"], "util.tf_export.tf_export": [], "framework.load_library.load_op_library": ["hashlib.sha1", "client.pywrap_tf_session.TF_GetOpList", "framework._pywrap_python_op_gen.GetPythonWrappers", "client.pywrap_tf_session.TF_LoadLibrary", "<builtin>.setattr", "importlib.machinery.ModuleSpec", "client.pywrap_tf_session.TF_DeleteLibraryHandle", "<builtin>.exec", "importlib.util.module_from_spec"], "client.pywrap_tf_session.TF_LoadLibrary": [], "client.pywrap_tf_session.TF_GetOpList": [], "framework._pywrap_python_op_gen.GetPythonWrappers": [], "client.pywrap_tf_session.TF_DeleteLibraryHandle": [], "hashlib.sha1": [], "importlib.machinery.ModuleSpec": [], "importlib.util.module_from_spec": [], "<builtin>.exec": [], "<builtin>.setattr": [], "util.deprecation.deprecated": [], "framework.load_library.load_file_system_library": ["client.pywrap_tf_session.TF_LoadLibrary"], "framework.load_library._is_shared_object": ["platform.system"], "platform.system": [], "framework.load_library.load_library": ["client.pywrap_tf_session.TF_LoadLibrary", "client.pywrap_tf_session.TF_LoadLibrary", "os.path.exists", "os.path.isdir", "os.listdir", "os.path.join", "<builtin>.OSError"], "os.path.exists": [], "os.path.isdir": [], "os.listdir": [], "os.path.join": [], "<builtin>.OSError": [], "framework.load_library.load_pluggable_device_library": ["client.pywrap_tf_session.TF_LoadLibrary", "os.path.exists", "eager.context.context", "os.path.isdir", "client.pywrap_tf_session.TF_LoadPluggableDeviceLibrary", "os.listdir", "os.path.join", "<builtin>.OSError"], "client.pywrap_tf_session.TF_LoadPluggableDeviceLibrary": [], "eager.context.context": [], "framework.load_library.register_filesystem_plugin": ["<builtin>.OSError", "os.path.exists", "client.pywrap_tf_session.TF_RegisterFilesystemPlugin"], "client.pywrap_tf_session.TF_RegisterFilesystemPlugin": []}