{"util.compat": ["util.tf_export.tf_export"], "util.compat.as_bytes": ["<builtin>.isinstance", "<builtin>.TypeError", "<builtin>.bytes"], "<builtin>.isinstance": [], "<builtin>.bytes": [], "<builtin>.TypeError": [], "util.compat.as_text": ["<builtin>.isinstance", "<builtin>.TypeError"], "util.compat.as_str": ["util.tf_export.tf_export", "util.tf_export.tf_export"], "util.tf_export.tf_export": [], "util.compat.as_str_any": ["<builtin>.isinstance", "<builtin>.str", "util.tf_export.tf_export"], "<builtin>.str": [], "util.compat.path_to_str": ["util.tf_export.tf_export", "<builtin>.hasattr"], "<builtin>.hasattr": [], "util.compat.path_to_bytes": ["util.tf_export.tf_export", "<builtin>.hasattr"]}