{"ops.linalg_grad": ["framework.ops.RegisterGradient"], "framework.ops.RegisterGradient": [], "ops.linalg_grad._MatrixInverseGrad": ["ops.math_ops.matmul"], "ops.math_ops.matmul": [], "ops.linalg_grad._EinsumGrad": ["<builtin>.isinstance", "ops.gen_linalg_ops.einsum", "ops.array_ops.broadcast_gradient_args", "ops.math_ops.reduce_sum", "ops.linalg_grad._EinsumGrad._GetGradReduced", "ops.array_ops.reshape", "ops.math_ops.conj", "ops.linalg_grad._EinsumGrad._GetGradWrt", "ops.linalg_grad._EinsumGrad._GetBcastSubshape", "<builtin>.set", "ops.array_ops.shape", "<builtin>.len"], "ops.linalg_grad._EinsumGrad._GetAxisFromLabel": ["<builtin>.len"], "<builtin>.len": [], "ops.linalg_grad._EinsumGrad._GetBcastSubshape": ["<builtin>.len"], "ops.linalg_grad._EinsumGrad._GetReducedSubscripts": ["<builtin>.list", "ops.array_ops.stack", "ops.linalg_grad._EinsumGrad._GetAxisFromLabel"], "<builtin>.list": [], "ops.array_ops.stack": [], "ops.linalg_grad._EinsumGrad._GetGradReduced": ["ops.array_ops.concat", "ops.gen_linalg_ops.einsum", "ops.array_ops.broadcast_to", "ops.array_ops.reshape", "framework.ops.convert_to_tensor", "ops.math_ops.reduced_shape", "ops.linalg_grad._EinsumGrad._GetReducedSubscripts", "ops.array_ops.ones", "<builtin>.set", "ops.array_ops.shape", "<builtin>.len"], "<builtin>.set": [], "framework.ops.convert_to_tensor": [], "ops.math_ops.reduced_shape": [], "ops.array_ops.reshape": [], "ops.array_ops.broadcast_to": [], "ops.array_ops.shape": [], "ops.array_ops.concat": [], "ops.array_ops.ones": [], "ops.gen_linalg_ops.einsum": [], "ops.linalg_grad._EinsumGrad._GetGradWrt": ["ops.gen_linalg_ops.einsum", "<builtin>.set", "ops.linalg_grad._EinsumGrad._GetGradReduced"], "<builtin>.isinstance": [], "ops.math_ops.conj": [], "ops.array_ops.broadcast_gradient_args": [], "ops.math_ops.reduce_sum": [], "ops.linalg_grad._MatrixDeterminantGrad": ["ops.linalg_ops.matrix_inverse", "ops.array_ops.concat", "ops.array_ops.shape", "ops.array_ops.reshape"], "ops.linalg_ops.matrix_inverse": [], "ops.linalg_grad._MatrixSquareRootGrad": ["ops.math_ops.add", "ops.array_ops.concat", "ops.array_ops.tile", "ops.array_ops.reshape", "ops.linalg_ops.matrix_solve", "ops.math_ops.subtract", "ops.math_ops.reduce_prod", "ops.linalg_grad._MatrixSquareRootGrad._KroneckerProduct", "ops.array_ops.slice", "ops.array_ops.size", "ops.linalg_ops.eye", "ops.array_ops.shape", "ops.array_ops.matrix_transpose"], "ops.linalg_grad._MatrixSquareRootGrad._KroneckerProduct": ["ops.array_ops.concat", "ops.array_ops.shape", "ops.array_ops.reshape", "ops.math_ops.subtract", "ops.array_ops.slice", "ops.array_ops.size"], "ops.array_ops.size": [], "ops.math_ops.subtract": [], "ops.array_ops.slice": [], "ops.math_ops.reduce_prod": [], "ops.linalg_ops.eye": [], "ops.array_ops.tile": [], "ops.array_ops.matrix_transpose": [], "ops.math_ops.add": [], "ops.linalg_ops.matrix_solve": [], "ops.linalg_grad._LogMatrixDeterminantGrad": ["ops.linalg_ops.matrix_inverse", "ops.array_ops.concat", "ops.array_ops.shape", "ops.array_ops.reshape"], "ops.linalg_grad._CholeskyGrad": ["ops.array_ops.matrix_band_part", "ops.math_ops.matmul", "ops.linalg_ops.matrix_triangular_solve", "linalg.linalg_impl.adjoint", "ops.linalg_ops.eye", "ops.array_ops.shape", "ops.array_ops.matrix_diag_part", "ops.array_ops.matrix_set_diag"], "ops.linalg_ops.matrix_triangular_solve": [], "ops.array_ops.matrix_diag_part": [], "ops.array_ops.matrix_set_diag": [], "ops.array_ops.matrix_band_part": [], "linalg.linalg_impl.adjoint": [], "ops.linalg_grad._QrGrad": ["ops.math_ops.matmul", "ops.linalg_grad._QrGrad._QrGradSquareAndDeepMatrices", "<builtin>.NotImplementedError", "ops.array_ops.concat"], "<builtin>.NotImplementedError": [], "ops.linalg_grad._QrGrad._TriangularSolve": ["ops.linalg_ops.matrix_triangular_solve", "linalg.linalg_impl.adjoint"], "ops.linalg_grad._QrGrad._QrGradSquareAndDeepMatrices": ["ops.math_ops.real", "ops.array_ops.matrix_band_part", "ops.math_ops.matmul", "ops.math_ops.cast", "ops.array_ops.zeros_like", "ops.linalg_grad._QrGrad._TriangularSolve", "linalg.linalg_impl.set_diag", "linalg.linalg_impl.diag_part", "linalg.linalg_impl.adjoint"], "ops.array_ops.zeros_like": [], "linalg.linalg_impl.diag_part": [], "linalg.linalg_impl.set_diag": [], "ops.math_ops.real": [], "ops.math_ops.cast": [], "ops.linalg_grad._MatrixSolveGrad": ["ops.math_ops.matmul", "ops.linalg_ops.matrix_solve"], "ops.linalg_grad._MatrixSolveLsGrad": ["ops.linalg_grad._MatrixSolveLsGrad._Underdetermined", "ops.control_flow_ops.cond", "ops.linalg_grad._MatrixSolveLsGrad._Overdetermined", "ops.array_ops.shape", "<builtin>.ValueError"], "ops.linalg_grad._MatrixSolveLsGrad._Overdetermined": ["ops.math_ops.matmul", "ops.math_ops.cast", "ops.linalg_ops.cholesky_solve", "ops.linalg_ops._RegularizedGramianCholesky", "ops.array_ops.matrix_transpose"], "ops.linalg_ops._RegularizedGramianCholesky": [], "ops.linalg_ops.cholesky_solve": [], "ops.linalg_grad._MatrixSolveLsGrad._Underdetermined": ["ops.math_ops.matmul", "ops.math_ops.cast", "ops.linalg_ops.cholesky_solve", "ops.linalg_ops._RegularizedGramianCholesky"], "<builtin>.ValueError": [], "ops.linalg_grad._MatrixSolveLsGrad.<lambda1>": ["ops.linalg_grad._MatrixSolveLsGrad._Overdetermined"], "ops.linalg_grad._MatrixSolveLsGrad.<lambda2>": ["ops.linalg_grad._MatrixSolveLsGrad._Underdetermined"], "ops.control_flow_ops.cond": [], "ops.linalg_grad._BandedTriangularSolveGrad": ["ops.array_ops.broadcast_gradient_args", "ops.math_ops.reduce_sum", "ops.array_ops.reshape", "ops.math_ops.matmul", "ops.array_ops.shape", "ops.linalg_ops.banded_triangular_solve", "ops.array_ops.matrix_diag_part"], "ops.linalg_ops.banded_triangular_solve": [], "ops.linalg_grad._MatrixTriangularSolveGrad": ["ops.array_ops.broadcast_gradient_args", "ops.array_ops.matrix_band_part", "ops.math_ops.reduce_sum", "ops.array_ops.reshape", "ops.math_ops.matmul", "ops.linalg_ops.matrix_triangular_solve", "ops.array_ops.shape"], "ops.linalg_grad._SafeReciprocal": ["ops.math_ops.reciprocal"], "ops.math_ops.reciprocal": [], "ops.linalg_grad._EigGrad": ["ops.math_ops.real", "ops.linalg_grad._SafeReciprocal", "ops.math_ops.matmul", "ops.array_ops.matrix_diag", "ops.linalg_ops.matrix_solve", "ops.math_ops.cast", "ops.array_ops.zeros_like", "ops.math_ops.conj", "ops.linalg_ops.eig", "linalg.linalg_impl.adjoint", "framework.ops.control_dependencies", "ops.array_ops.expand_dims", "ops.array_ops.matrix_diag_part", "ops.array_ops.matrix_set_diag"], "framework.ops.control_dependencies": [], "ops.array_ops.expand_dims": [], "ops.array_ops.matrix_diag": [], "ops.linalg_ops.eig": [], "ops.linalg_grad._SelfAdjointEigV2Grad": ["ops.array_ops.matrix_band_part", "ops.linalg_grad._SafeReciprocal", "ops.array_ops.matrix_diag", "ops.math_ops.matmul", "ops.array_ops.zeros_like", "ops.linalg_ops.self_adjoint_eig", "linalg.linalg_impl.adjoint", "framework.ops.control_dependencies", "ops.array_ops.expand_dims", "ops.array_ops.matrix_diag_part", "ops.array_ops.matrix_set_diag"], "ops.linalg_ops.self_adjoint_eig": [], "ops.linalg_grad._SvdGrad": ["ops.array_ops.expand_dims", "linalg.linalg_impl.eye", "ops.linalg_grad._SafeReciprocal", "ops.array_ops.matrix_diag", "ops.math_ops.matmul", "ops.math_ops.cast", "ops.array_ops.zeros_like", "<builtin>.NotImplementedError", "ops.array_ops.matrix_transpose", "ops.linalg_ops.svd", "framework.ops.control_dependencies", "ops.math_ops.square", "linalg.linalg_impl.adjoint", "<builtin>.abs", "ops.array_ops.shape", "ops.array_ops.matrix_set_diag"], "ops.linalg_ops.svd": [], "<builtin>.abs": [], "ops.math_ops.square": [], "linalg.linalg_impl.eye": [], "ops.linalg_grad._LeftShift": ["ops.array_ops.concat", "ops.array_ops.rank", "ops.array_ops.pad", "ops.array_ops.zeros", "ops.array_ops.constant"], "ops.array_ops.rank": [], "ops.array_ops.zeros": [], "ops.array_ops.constant": [], "ops.array_ops.pad": [], "ops.linalg_grad._RightShift": ["ops.array_ops.concat", "ops.array_ops.rank", "ops.array_ops.pad", "ops.array_ops.zeros", "ops.array_ops.constant"], "ops.linalg_grad._TridiagonalMatMulGrad": ["ops.linalg_grad._LeftShift", "ops.linalg_grad._RightShift", "ops.math_ops.reduce_sum", "ops.math_ops.conj", "ops.array_ops.expand_dims", "ops.array_ops.matrix_transpose"], "ops.linalg_grad._TridiagonalSolveGrad": ["ops.linalg_grad._TransposeTridiagonalMatrix", "ops.linalg_ops.tridiagonal_solve", "ops.linalg_grad._MatmulExtractingThreeDiagonals"], "ops.linalg_grad._TransposeTridiagonalMatrix": ["ops.array_ops.concat", "ops.array_ops.stack", "ops.array_ops.rank", "<builtin>.list", "ops.array_ops.pad", "ops.array_ops.zeros", "ops.array_ops.constant"], "ops.linalg_ops.tridiagonal_solve": [], "ops.linalg_grad._MatmulExtractingThreeDiagonals": ["ops.array_ops.concat", "ops.array_ops.stack", "ops.array_ops.rank", "ops.math_ops.reduce_sum", "<builtin>.list", "ops.array_ops.pad", "ops.array_ops.zeros", "ops.array_ops.constant"]}