{"model_utils.export_output": [], "model_utils.export_output.ExportOutput": ["abc.abstractmethod"], "abc.abstractmethod": [], "model_utils.export_output.ExportOutput.as_signature_def": [], "model_utils.export_output.ExportOutput._check_output_key": ["<builtin>.isinstance", "<builtin>.ValueError"], "<builtin>.isinstance": [], "<builtin>.ValueError": [], "model_utils.export_output.ExportOutput._wrap_and_check_outputs": ["model_utils.export_output.ExportOutput._check_output_key", "<builtin>.isinstance", "<builtin>.ValueError"], "model_utils.export_output.ClassificationOutput.__init__": ["<builtin>.isinstance", "framework.dtypes.as_dtype", "<builtin>.ValueError"], "framework.dtypes.as_dtype": [], "model_utils.export_output.ClassificationOutput.scores": [], "model_utils.export_output.ClassificationOutput.classes": [], "model_utils.export_output.ClassificationOutput.as_signature_def": ["<builtin>.len", "framework.dtypes.as_dtype", "saved_model.signature_def_utils.classification_signature_def", "<builtin>.ValueError"], "<builtin>.len": [], "saved_model.signature_def_utils.classification_signature_def": [], "model_utils.export_output.RegressionOutput.__init__": ["<builtin>.isinstance", "<builtin>.ValueError"], "model_utils.export_output.RegressionOutput.value": [], "model_utils.export_output.RegressionOutput.as_signature_def": ["<builtin>.len", "saved_model.signature_def_utils.regression_signature_def", "framework.dtypes.as_dtype", "<builtin>.ValueError"], "saved_model.signature_def_utils.regression_signature_def": [], "model_utils.export_output.PredictOutput.__init__": ["model_utils.export_output.ExportOutput._wrap_and_check_outputs"], "model_utils.export_output.PredictOutput.outputs": [], "model_utils.export_output.PredictOutput.as_signature_def": ["saved_model.signature_def_utils.predict_signature_def"], "saved_model.signature_def_utils.predict_signature_def": [], "model_utils.export_output._SupervisedOutput.__init__": ["model_utils.export_output._SupervisedOutput._prefix_output_keys", "model_utils.export_output.ExportOutput._wrap_and_check_outputs", "model_utils.export_output._SupervisedOutput._wrap_and_check_metrics"], "model_utils.export_output._SupervisedOutput._prefix_output_keys": ["model_utils.export_output._SupervisedOutput._prefix_key"], "model_utils.export_output._SupervisedOutput._wrap_and_check_metrics": ["framework.constant_op.constant", "framework.tensor_util.is_tf_type", "<builtin>.len", "framework.ops.control_dependencies", "model_utils.export_output.ExportOutput._check_output_key", "model_utils.export_output._SupervisedOutput._prefix_key", "<builtin>.ValueError", "<builtin>.isinstance"], "model_utils.export_output._SupervisedOutput._prefix_key": [], "framework.tensor_util.is_tf_type": [], "framework.ops.control_dependencies": [], "framework.constant_op.constant": [], "model_utils.export_output._SupervisedOutput.loss": [], "model_utils.export_output._SupervisedOutput.predictions": [], "model_utils.export_output._SupervisedOutput.metrics": [], "model_utils.export_output._SupervisedOutput": ["abc.abstractmethod"], "model_utils.export_output._SupervisedOutput._get_signature_def_fn": [], "model_utils.export_output._SupervisedOutput.as_signature_def": ["model_utils.export_output._SupervisedOutput._get_signature_def_fn"], "model_utils.export_output.TrainOutput._get_signature_def_fn": [], "model_utils.export_output.EvalOutput._get_signature_def_fn": []}