{"Desktop\\Work\\tensorflow-master\\tensorflow\\python\\debug\\lib\\common": ["collections.namedtuple"], "collections.namedtuple": [], "Desktop\\Work\\tensorflow-master\\tensorflow\\python\\debug\\lib\\common.get_graph_element_name": ["<builtin>.str", "<builtin>.hasattr"], "<builtin>.hasattr": [], "<builtin>.str": [], "Desktop\\Work\\tensorflow-master\\tensorflow\\python\\debug\\lib\\common.get_flattened_names": ["Desktop\\Work\\tensorflow-master\\tensorflow\\python\\debug\\lib\\common.get_flattened_names", "<builtin>.isinstance", "Desktop\\Work\\tensorflow-master\\tensorflow\\python\\debug\\lib\\common.get_graph_element_name"], "<builtin>.isinstance": [], "Desktop\\Work\\tensorflow-master\\tensorflow\\python\\debug\\lib\\common.get_run_key": ["Desktop\\Work\\tensorflow-master\\tensorflow\\python\\debug\\lib\\common.get_flattened_names", "json.dumps"], "json.dumps": []}
